zulip_botserver/__init__.py
zulip_botserver/input_parameters.py
zulip_botserver/py.typed
zulip_botserver/server.py
zulip_botserver-0.9.0.dist-info/METADATA
zulip_botserver-0.9.0.dist-info/WHEEL
zulip_botserver-0.9.0.dist-info/entry_points.txt
zulip_botserver-0.9.0.dist-info/top_level.txt
zulip_botserver-0.9.0.dist-info/RECORD
