Metadata-Version: 2.1
Name: zulip-botserver
Version: 0.9.0
Summary: Zulip's Flask server for running bots
Home-page: https://www.zulip.org/
Author: Zulip Open Source Project
Author-email: zulip-devel@googlegroups.com
Project-URL: Source, https://github.com/zulip/python-zulip-api/
Project-URL: Documentation, https://zulip.com/api
Classifier: Development Status :: 4 - Beta
Classifier: Environment :: Web Environment
Classifier: Intended Audience :: Developers
Classifier: License :: OSI Approved :: Apache Software License
Classifier: Topic :: Communications :: Chat
Classifier: Programming Language :: Python :: 3
Classifier: Programming Language :: Python :: 3.8
Classifier: Programming Language :: Python :: 3.9
Classifier: Programming Language :: Python :: 3.10
Classifier: Programming Language :: Python :: 3.11
Requires-Python: >=3.8
Requires-Dist: zulip
Requires-Dist: zulip-bots
Requires-Dist: flask >=0.12.2
Requires-Dist: typing-extensions >=4.5.0
